esguard/__init__.py
esguard/esguard.py
esguard-0.1.9.dist-info/WHEEL
esguard-0.1.9.dist-info/METADATA
esguard-0.1.9.dist-info/RECORD
