Metadata-Version: 2.1
Name: esguard
Version: 0.1.9
Summary: esguard provides a Python decorator that waits for processing while monitoring the load of Elasticsearch.
Home-page: http://github.com/po3rin/esguard
License: Apache-2.0
Author: po3rin
Requires-Python: >=3.7,<4.0
Classifier: License :: OSI Approved :: Apache Software License
Classifier: Programming Language :: Python :: 3
Classifier: Programming Language :: Python :: 3.7
Classifier: Programming Language :: Python :: 3.8
Classifier: Programming Language :: Python :: 3.9
Requires-Dist: docker (>=5.0.0,<6.0.0)
Requires-Dist: elasticsearch (>=7.12.1,<8.0.0)
Requires-Dist: six (>=1.16.0,<2.0.0)
Requires-Dist: tenacity (>=8.0.1,<9.0.0)
Project-URL: Repository, http://github.com/po3rin/esguard
